triqs_maxent/__init__.py
triqs_maxent/alpha_meshes.py
triqs_maxent/default_models.py
triqs_maxent/elementwise_maxent.py
triqs_maxent/functions.py
triqs_maxent/kernels.py
triqs_maxent/logtaker.py
triqs_maxent/maxent_loop.py
triqs_maxent/maxent_result.py
triqs_maxent/maxent_util.py
triqs_maxent/omega_meshes.py
triqs_maxent/plot_utils.py
triqs_maxent/preblur.py
triqs_maxent/probabilities.py
triqs_maxent/sigma_continuator.py
triqs_maxent/tau_maxent.py
triqs_maxent/test_util.py
triqs_maxent/version.py
triqs_maxent/analyzers/__init__.py
triqs_maxent/analyzers/analyzer.py
triqs_maxent/analyzers/bryan_analyzer.py
triqs_maxent/analyzers/chi2_curvature_analyzer.py
triqs_maxent/analyzers/classic_analyzer.py
triqs_maxent/analyzers/entropy_analyzer.py
triqs_maxent/analyzers/linefit_analyzer.py
triqs_maxent/cost_functions/__init__.py
triqs_maxent/cost_functions/bryan_cost_function.py
triqs_maxent/cost_functions/cost_function.py
triqs_maxent/cost_functions/maxent_cost_function.py
triqs_maxent/minimizers/__init__.py
triqs_maxent/minimizers/convergence_methods.py
triqs_maxent/minimizers/levenberg_minimizer.py
triqs_maxent/minimizers/minimizer.py
triqs_maxent/plot/__init__.py
triqs_maxent/plot/jupyter_plot_maxent.py
triqs_maxent/plot/plot_maxent.py
triqs_maxent-3.3.0.dist-info/COPYING.txt
triqs_maxent-3.3.0.dist-info/LICENSE
triqs_maxent-3.3.0.dist-info/LICENSE.txt
triqs_maxent-3.3.0.dist-info/METADATA
triqs_maxent-3.3.0.dist-info/WHEEL
triqs_maxent-3.3.0.dist-info/top_level.txt
triqs_maxent-3.3.0.dist-info/RECORD
