Metadata-Version: 2.1
Name: triqs_maxent
Version: 3.3.0
Summary: TRIQS application providing a modular Maximum Entropy progra to perform analytic continuation based on the TRIQS library (triqs.github.io)
Author-email: TRIQS <triqs@flatironinstitute.org>
Project-URL: Homepage, https://triqs.github.io/maxent
Project-URL: Bug Tracker, https://github.com/triqs/maxent/issues
Keywords: triqs,analytic-continuation,maximum-entropy
Classifier: Programming Language :: Python :: 3
Classifier: License :: OSI Approved :: GNU General Public License v3 (GPLv3)
Classifier: Operating System :: OS Independent
Requires-Python: >=3.7
License-File: LICENSE
License-File: LICENSE.txt
License-File: COPYING.txt
Requires-Dist: numpy
Requires-Dist: scipy
Requires-Dist: matplotlib
